CHANGELOG.md
LICENSE
MANIFEST.in
README.md
requirements-dev.txt
setup.cfg
setup.py
chpip/__init__.py
chpip/__main__.py
chpip/core.py
chpip/exception.py
chpip/utils.py
chpip.egg-info/PKG-INFO
chpip.egg-info/SOURCES.txt
chpip.egg-info/dependency_links.txt
chpip.egg-info/entry_points.txt
chpip.egg-info/requires.txt
chpip.egg-info/top_level.txt
tests/__init__.py
tests/conftest.py
tests/test_change_index.py
tests/test_set_index.py